{"name":"login with role system support of headquarter","testSteps":[{"number":1,"description":"[1] {username\u003d4009906, password\u003d123456, lang\u003den}","duration":8034,"startTime":1478137256224,"screenshots":[{"screenshot":"f7ea410409fc41239c2ba170f097e62b.png"}],"result":"SUCCESS","children":[{"number":2,"description":"Given I logout from system","duration":868,"startTime":1478137256225,"screenshots":[{"screenshot":"11a559e42be2288ea577d4ee9621526d.png"}],"result":"SUCCESS"},{"number":3,"description":"Given I open Login page","duration":674,"startTime":1478137257098,"screenshots":[{"screenshot":"35bea53004f39eed20d942bf48fa3e71.png"}],"result":"SUCCESS"},{"number":4,"description":"When I input my credentials username 4009906 and password 123456","duration":2774,"startTime":1478137257772,"screenshots":[{"screenshot":"688c8a42e2926a0ab7262b8bc41c6d3f.png"},{"screenshot":"9902be2b8095acacc171e2b41f033351.png"}],"result":"SUCCESS"},{"number":5,"description":"Then The system should let me in","duration":271,"startTime":1478137260547,"screenshots":[{"screenshot":"9902be2b8095acacc171e2b41f033351.png"}],"result":"SUCCESS"},{"number":6,"description":"When I change language to en","duration":1724,"startTime":1478137260818,"screenshots":[{"screenshot":"24c801513b57067f5ad4848949c615b0.png"}],"result":"SUCCESS"},{"number":7,"description":"Then The system should change all text to en","duration":190,"startTime":1478137262542,"screenshots":[{"screenshot":"24c801513b57067f5ad4848949c615b0.png"}],"result":"SUCCESS"},{"number":8,"description":"Given List menu I have permission\n| Credit Management | Accounting |\n| Maintain Credit Data | Accounting |\n| Branch Management | Common |\n| SANSAN Import | Import/Export |\n| BASS Export | Import/Export |\n| Company Management | Common |\n| Summary Report | Report |\n| Register | Daily Report |\n| Search History | Daily Report |\n| Search By Date | Daily Report |\n| Employee Management | Common |\n| Program Test | Import/Export |\n| Integration Test | Import/Export |","duration":113,"startTime":1478137262732,"screenshots":[{"screenshot":"24c801513b57067f5ad4848949c615b0.png"}],"result":"SUCCESS"},{"number":9,"description":"Then The system should show all menu I have permission","duration":1164,"startTime":1478137262845,"screenshots":[{"screenshot":"f7ea410409fc41239c2ba170f097e62b.png"}],"result":"SUCCESS"},{"number":10,"description":"And The system should show only menu I have permission","duration":135,"startTime":1478137264010,"screenshots":[{"screenshot":"f7ea410409fc41239c2ba170f097e62b.png"}],"result":"SUCCESS"}]}],"userStory":{"id":"verify-all-menus-by-user-role","storyName":"Verify all menus by user role","path":"menu/verify_all_menus.feature","narrative":"As an user\nI want to be able to change menu when i change role of user\nSo that I can understand system","type":"feature"},"title":"login with role system support of headquarter","description":"","backgroundTitle":"","backgroundDescription":"","additionalIssues":["","","","","","",""],"tags":[{"name":"Menu","type":"capability"},{"name":"3.1.5","type":"version"},{"name":"","type":"issue"},{"name":"Menu/Verify all menus by user role","type":"feature"},{"name":"Sprint-1.1","type":"version"}],"startTime":1478137256224,"duration":8034,"sessionId":"5b71eda647b661547891f68af05fa8d4","driver":"chrome","dataTable":{"headers":["username","password","lang"],"rows":[{"values":["4009906","123456","en"],"result":"SUCCESS"}],"predefinedRows":true,"currentRow":{"value":0},"dataSetDescriptors":[{"startRow":0,"rowCount":0,"name":"","description":""}]},"manual":false,"result":"SUCCESS","issues":["","","","","","",""],"versions":["3.1.5","Sprint-1.1"]}