{"name":"verify edit daily report","testSteps":[{"number":1,"description":"[1] {submenuText\u003dSearch By Date, menuText\u003dDaily Report, buttonSearchText\u003dSearch, branchName\u003d東京都, employeeInfo\u003d9999999, editButtonText\u003dEdit, rowIndex\u003d0, pageTitle\u003dDaily Report}","duration":10399,"startTime":1478137177057,"screenshots":[{"screenshot":"4de85f3834e8d6155ca17a5503924df8.png"},{"screenshot":"8d57da6b8052b32d65feb8aee78d253a.png"}],"result":"SUCCESS","children":[{"number":2,"description":"When I open submenu Search By Date of menu Daily Report","duration":910,"startTime":1478137181758,"screenshots":[{"screenshot":"d7b5a0b36c6e3e43d6baaa99b42d1886.png"}],"result":"SUCCESS"},{"number":3,"description":"And In Search by date screen, I choose a branch 東京都 in dropdown Branch","duration":857,"startTime":1478137182668,"screenshots":[{"screenshot":"ef82a533f0d6293f76cf817aa564322b.png"}],"result":"SUCCESS"},{"number":4,"description":"And In Search by date screen, I type value 9999999 for autocomplete Employee","duration":244,"startTime":1478137183525,"screenshots":[{"screenshot":"e33ee9da8af34166ab9b5f8287ca81d3.png"}],"result":"SUCCESS"},{"number":5,"description":"And In Search by date screen, I choose 9999999 employee in dropdown of autocomplete Employee","duration":1478,"startTime":1478137183769,"screenshots":[{"screenshot":"eb2602e93425f038d696cac41f490c45.png"}],"result":"SUCCESS"},{"number":6,"description":"And In Search by date screen, I click button \u0027Search\u0027","duration":788,"startTime":1478137185248,"screenshots":[{"screenshot":"4dae7b37bd05280ede60099d056f775c.png"}],"result":"SUCCESS"},{"number":7,"description":"And In Search by date screen, I select row 0","duration":247,"startTime":1478137186036,"screenshots":[{"screenshot":"a80a8085dbefb0e2f29d57427b396d08.png"}],"result":"SUCCESS"},{"number":8,"description":"And In Search by date screen, I click button \u0027Edit\u0027","duration":822,"startTime":1478137186283,"screenshots":[{"screenshot":"53b94e2c949543335f04a56da4e56e16.png"}],"result":"SUCCESS"},{"number":9,"description":"Then The system should open \u0027Daily Report\u0027 page","duration":237,"startTime":1478137187105,"screenshots":[{"screenshot":"8d57da6b8052b32d65feb8aee78d253a.png"}],"result":"SUCCESS"}]}],"userStory":{"id":"search-daily-report-by-date","storyName":"Search Daily report by date","path":"searchDailyReportByDate/searchDailyReportByDate.feature","narrative":"As a user\nI want search daily report by date\nSo I can view detail, delete or edit daily report","type":"feature"},"title":"verify edit daily report","description":"","additionalIssues":["","","","","","","",""],"tags":[{"name":"3.1.5","type":"version"},{"name":"Search daily report by date","type":"capability"},{"name":"Search daily report by date/Search daily report by date","type":"feature"},{"name":"","type":"issue"},{"name":"LoggedIn","type":"tag"},{"name":"Search Daily report by date","type":"feature"},{"name":"Sprint-1.1","type":"version"}],"startTime":1478137177057,"duration":10399,"sessionId":"9c5954d4ef1ac2845c372d3f713dec30","driver":"chrome","dataTable":{"headers":["submenuText","menuText","buttonSearchText","branchName","employeeInfo","editButtonText","rowIndex","pageTitle"],"rows":[{"values":["Search By Date","Daily Report","Search","東京都","9999999","Edit","0","Daily Report"],"result":"SUCCESS"}],"predefinedRows":true,"currentRow":{"value":0},"dataSetDescriptors":[{"startRow":0,"rowCount":0,"name":"","description":""}]},"manual":false,"result":"SUCCESS","issues":["","","","","","","",""],"versions":["3.1.5","Sprint-1.1"]}