{"name":"verify delete daily report with user is manager","testSteps":[{"number":1,"description":"[1] {submenuText\u003dSearch By Date, menuText\u003dDaily Report, buttonSearchText\u003dSearch, branchName\u003d東京都, employeeInfo\u003d9999999, deleteButtonText\u003dDelete, rowIndex\u003d0, noButtonText\u003dNo, yesButtonText\u003dYes}","duration":17640,"startTime":1478137188277,"screenshots":[{"screenshot":"4de85f3834e8d6155ca17a5503924df8.png"},{"screenshot":"46ff1015e256fdb44bbd13ab3dff7c15.png"}],"result":"SUCCESS","children":[{"number":2,"description":"When I open submenu Search By Date of menu Daily Report","duration":895,"startTime":1478137192845,"screenshots":[{"screenshot":"a3adb86fd5e89fb5a7814bcd94055485.png"}],"result":"SUCCESS"},{"number":3,"description":"And In Search by date screen, I choose a branch 東京都 in dropdown Branch","duration":823,"startTime":1478137193741,"screenshots":[{"screenshot":"ef82a533f0d6293f76cf817aa564322b.png"}],"result":"SUCCESS"},{"number":4,"description":"And In Search by date screen, I type value 9999999 for autocomplete Employee","duration":238,"startTime":1478137194564,"screenshots":[{"screenshot":"e33ee9da8af34166ab9b5f8287ca81d3.png"}],"result":"SUCCESS"},{"number":5,"description":"And In Search by date screen, I choose 9999999 employee in dropdown of autocomplete Employee","duration":1413,"startTime":1478137194802,"screenshots":[{"screenshot":"eb2602e93425f038d696cac41f490c45.png"}],"result":"SUCCESS"},{"number":6,"description":"And In Search by date screen, I click button \u0027Search\u0027","duration":777,"startTime":1478137196215,"screenshots":[{"screenshot":"411266707d7736ddee662e2f87936537.png"}],"result":"SUCCESS"},{"number":7,"description":"And In Search by date screen, I select row 0","duration":270,"startTime":1478137196993,"screenshots":[{"screenshot":"a80a8085dbefb0e2f29d57427b396d08.png"}],"result":"SUCCESS"},{"number":8,"description":"And In Search by date screen, I click button \u0027Delete\u0027","duration":233,"startTime":1478137197263,"screenshots":[{"screenshot":"35ffdb99e2c5eaab03711ca725bd91d1.png"}],"result":"SUCCESS"},{"number":9,"description":"Then The system should show confirm delete popup","duration":156,"startTime":1478137197497,"screenshots":[{"screenshot":"35ffdb99e2c5eaab03711ca725bd91d1.png"}],"result":"SUCCESS"},{"number":10,"description":"When In Search by date screen, I click button \u0027No\u0027 in confirm delete popup","duration":205,"startTime":1478137197654,"screenshots":[{"screenshot":"18376cd173764632bb8da5b980e4539b.png"}],"result":"SUCCESS"},{"number":11,"description":"Then The system should show table Search by date result has record found","duration":148,"startTime":1478137197859,"screenshots":[{"screenshot":"18376cd173764632bb8da5b980e4539b.png"}],"result":"SUCCESS"},{"number":12,"description":"When In Search by date screen, I click button \u0027Delete\u0027","duration":211,"startTime":1478137198008,"screenshots":[{"screenshot":"e0f20afc4309425a5f7243cd283fd88d.png"}],"result":"SUCCESS"},{"number":13,"description":"And In Search by date screen, I click button \u0027Yes\u0027 in confirm delete popup","duration":851,"startTime":1478137198220,"screenshots":[{"screenshot":"b04e830e53207ada4446cba80b6e4a29.png"}],"result":"SUCCESS"},{"number":14,"description":"Then The system should show message delete successfully","duration":6728,"startTime":1478137199072,"screenshots":[{"screenshot":"46ff1015e256fdb44bbd13ab3dff7c15.png"}],"result":"SUCCESS"}]}],"userStory":{"id":"search-daily-report-by-date","storyName":"Search Daily report by date","path":"searchDailyReportByDate/searchDailyReportByDate.feature","narrative":"As a user\nI want search daily report by date\nSo I can view detail, delete or edit daily report","type":"feature"},"title":"verify delete daily report with user is manager","description":"","additionalIssues":["","","","","","","","",""],"tags":[{"name":"3.1.5","type":"version"},{"name":"Search daily report by date","type":"capability"},{"name":"Search daily report by date/Search daily report by date","type":"feature"},{"name":"","type":"issue"},{"name":"LoggedIn","type":"tag"},{"name":"Search Daily report by date","type":"feature"},{"name":"Sprint-1.1","type":"version"}],"startTime":1478137188276,"duration":17641,"sessionId":"9c5954d4ef1ac2845c372d3f713dec30","driver":"chrome","dataTable":{"headers":["submenuText","menuText","buttonSearchText","branchName","employeeInfo","deleteButtonText","rowIndex","noButtonText","yesButtonText"],"rows":[{"values":["Search By Date","Daily Report","Search","東京都","9999999","Delete","0","No","Yes"],"result":"SUCCESS"}],"predefinedRows":true,"currentRow":{"value":0},"dataSetDescriptors":[{"startRow":0,"rowCount":0,"name":"","description":""}]},"manual":false,"result":"SUCCESS","issues":["","","","","","","","",""],"versions":["3.1.5","Sprint-1.1"]}